{"is_source_file": true, "format": "TypeScript (TSX)", "description": "This file defines a React functional component called Chessboard that renders a visual representation of a chessboard based on provided FEN string and move list properties.", "external_files": ["react"], "external_methods": ["React.FC"], "published": ["Move", "Chessboard"], "classes": [], "methods": [{"name": "Chessboard", "description": "React functional component that renders a styled chessboard div with a FEN display."}], "calls": [], "search-terms": ["React", "Chessboard", "FEN", "Move", "TSX", "Component", "src/components/Chessboard.tsx"], "state": 2, "file_id": 12, "knowledge_revision": 80, "git_revision": "307990677c056a6f06f94ba624c935cd61f6446c", "revision_history": [{"27": ""}, {"35": ""}, {"36": ""}, {"39": ""}, {"60": "af08cdfbf9bca2178f3d87ab1a1f67e6016ea07b"}, {"61": "af08cdfbf9bca2178f3d87ab1a1f67e6016ea07b"}, {"73": "307990677c056a6f06f94ba624c935cd61f6446c"}, {"76": "307990677c056a6f06f94ba624c935cd61f6446c"}, {"80": "307990677c056a6f06f94ba624c935cd61f6446c"}], "ctags": [], "hash": "0f6c264a9d9af92ba1fb0b5393eda9d6", "format-version": 4, "code-base-name": "chess_game_frontend", "filename": "chess_game_frontend/src/components/Chessboard.tsx"}